{
    "xmatter": [
        {
            "name": "xmatters-rest-api",
            "subComponents": [
                "workflows-and-communication-plans",
                "events-and-alerts",
                "roles-and-permissions",
                "versions",
                "authentication",
                "base-url",
                "accessing-data",
                "http-methods",
                "identifying-resources",
                "request-body-format",
                "character-encoding-in-requests",
                "response-format",
                "http-response-codes",
                "error-responses",
                "results-pagination",
                "special-characters-in-responses",
                "common-query-parameters",
                "common-fields",
                "common-objects"
            ]
        }
    ],
    "attachment": [
        {
            "name": "attachments",
            "subComponents": [
                "upload-an-attachment",
                "attachments-objects"
            ]
        }
    ],
    "audit": [
        {
            "name": "audits",
            "subComponents": [
                "audit-types",
                "get-event-audit-information",
                "audit-objects"
            ]
        }
    ],
    "change": [
        {
            "name": "change-intelligence",
            "subComponents": [
                "get-changes",
                "create-a-change-record",
                "change-objects"
            ]
        }
    ],
    "device": [
        {
            "name": "devices",
            "subComponents": [
                "get-a-device",
                "get-devices",
                "create-a-device",
                "modify-a-device",
                "delete-a-device",
                "device-objects"
            ]
        },
        {
            "name": "device-names",
            "subComponents": [
                "get-device-names",
                "create-a-device-name",
                "modify-a-device-name",
                "delete-a-device-name",
                "devicename-objects"
            ]
        },
        {
            "name": "device-types",
            "subComponents": [
                "get-device-types",
                "devicetypes-object"
            ]
        }
    ],
    "dynamic": [
        {
            "name": "dynamic-teams",
            "subComponents": [
                "get-dynamic-teams",
                "get-a-dynamic-team",
                "get-dynamic-team-members",
                "create-a-dynamic-team",
                "update-a-dynamic-team",
                "delete-a-dynamic-team",
                "dynamic-team-object"
            ]
        }
    ],
    "event": [
        {
            "name": "events",
            "subComponents": [
                "get-events",
                "get-an-event",
                "get-event-annotations",
                "get-an-event-annotation",
                "get-an-event-attachment",
                "get-user-delivery-data",
                "trigger-an-event",
                "add-a-comment-to-an-event",
                "change-the-status-of-an-event",
                "event-objects"
            ]
        },
        {
            "name": "event-suppressions",
            "subComponents": [
                "get-suppressed-events",
                "event-suppression-objects"
            ]
        }
    ],
    "external": [
        {
            "name": "external-conference-bridges",
            "subComponents": [
                "get-conference-bridges",
                "get-a-conference-bridge",
                "create-an-external-conference-bridge",
                "modify-a-conference-bridge",
                "delete-a-conference-bridge",
                "conference-bridge-objects"
            ]
        }
    ],
    "form": [
        {
            "name": "forms",
            "subComponents": [
                "get-forms",
                "get-forms-in-a-plan",
                "get-a-form-in-a-plan",
                "get-form-response-options",
                "get-form-sections",
                "create-a-plan-form",
                "create-form-message-templates",
                "create-form-response-options",
                "modify-a-plan-form",
                "modify-a-form-message-template",
                "modify-a-form-response-option",
                "form-objects"
            ]
        }
    ],
    "group": [
        {
            "name": "groups",
            "subComponents": [
                "get-a-group",
                "get-groups",
                "create-a-group",
                "modify-a-group",
                "delete-a-group",
                "get-a-group-39-s-supervisors",
                "get-group-license-quotas",
                "group-objects"
            ]
        },
        {
            "name": "group-roster",
            "subComponents": [
                "get-the-group-roster",
                "add-a-member-to-the-group-roster",
                "remove-a-member-from-the-group-roster"
            ]
        }
    ],
    "import": [
        {
            "name": "import-jobs",
            "subComponents": [
                "get-import-jobs",
                "get-an-import-job",
                "get-import-job-messages",
                "import-job-objects"
            ]
        }
    ],
    "incident": [
        {
            "name": "incidents",
            "subComponents": [
                "get-incidents",
                "get-an-incident",
                "trigger-an-incident",
                "create-an-incident",
                "modify-an-incident",
                "add-a-timeline-note",
                "incidents-objects"
            ]
        }
    ],
    "integration": [
        {
            "name": "integrations",
            "subComponents": [
                "get-an-integration",
                "get-integrations",
                "get-integration-logs",
                "create-an-integration",
                "modify-an-integration",
                "delete-an-integration",
                "integration-objects"
            ]
        }
    ],
    "oauth": [
        {
            "name": "oauth",
            "subComponents": [
                "obtain-an-access-token-and-refresh-token",
                "authorize-a-request",
                "refresh-an-access-token",
                "oauth-objects"
            ]
        }
    ],
    "on": [
        {
            "name": "on-call",
            "subComponents": [
                "get-who-is-on-call",
                "on-call-objects"
            ]
        },
        {
            "name": "on-call-summary",
            "subComponents": [
                "get-on-call-summary",
                "on-call-summary-objects"
            ]
        }
    ],
    "people": [
        {
            "name": "people",
            "subComponents": [
                "get-a-person-by-id",
                "get-a-person-by-query",
                "get-people",
                "create-a-person",
                "modify-a-person",
                "delete-a-person",
                "get-a-person-39-s-devices",
                "get-a-person-39-s-groups",
                "get-a-person-39-s-supervisors",
                "get-user-license-quotas",
                "person-objects"
            ]
        }
    ],
    "plan": [
        {
            "name": "plans",
            "subComponents": [
                "get-communication-plans",
                "get-a-communication-plan",
                "create-a-communication-plan",
                "modify-communication-plan",
                "delete-a-plan",
                "communication-plan-objects"
            ]
        },
        {
            "name": "plan-constants",
            "subComponents": [
                "get-plan-constants",
                "create-a-plan-constant",
                "modify-a-plan-constant",
                "delete-a-plan-constant",
                "plan-constant-objects"
            ]
        },
        {
            "name": "plan-endpoints",
            "subComponents": [
                "get-plan-endpoints",
                "create-plan-endpoint",
                "modify-a-plan-endpoint",
                "delete-a-plan-endpoint",
                "plan-endpoint-objects"
            ]
        },
        {
            "name": "plan-properties",
            "subComponents": [
                "get-plan-properties",
                "create-plan-properties",
                "modify-plan-properties",
                "plan-property-objects"
            ]
        }
    ],
    "role": [
        {
            "name": "roles",
            "subComponents": [
                "get-roles",
                "role-objects"
            ]
        }
    ],
    "scenario": [
        {
            "name": "scenarios",
            "subComponents": [
                "get-scenarios",
                "get-a-scenario",
                "get-scenarios-in-a-form",
                "get-a-scenario-attachment",
                "get-scenario-share-permissions",
                "create-a-scenario",
                "modify-a-scenario",
                "upload-attachment-to-a-scenario",
                "set-scenario-share-permissions",
                "scenario-objects"
            ]
        }
    ],
    "scheduled": [
        {
            "name": "scheduled-messages",
            "subComponents": [
                "get-scheduled-messages",
                "get-a-scheduled-message",
                "get-a-scheduled-message-attachment",
                "create-a-scheduled-message",
                "modify-a-scheduled-message",
                "delete-a-scheduled-message",
                "scheduled-message-objects"
            ]
        }
    ],
    "service": [
        {
            "name": "service-dependencies",
            "subComponents": [
                "get-service-dependencies",
                "create-a-service-dependency",
                "modify-a-service-dependency",
                "delete-a-service-dependency",
                "service-dependencies-objects"
            ]
        },
        {
            "name": "services",
            "subComponents": [
                "get-services",
                "get-a-service",
                "create-a-service",
                "modify-a-service",
                "delete-a-service",
                "services-objects"
            ]
        }
    ],
    "shared": [
        {
            "name": "shared-libraries",
            "subComponents": [
                "get-shared-libraries",
                "get-a-shared-library",
                "create-a-shared-library",
                "modify-a-shared-library",
                "delete-a-shared-library",
                "shared-library-objects"
            ]
        }
    ],
    "shift": [
        {
            "name": "shifts",
            "subComponents": [
                "get-a-shift",
                "get-shifts-in-a-group",
                "get-members-in-a-shift",
                "create-a-shift",
                "add-a-member-to-a-shift",
                "delete-a-shift",
                "shift-objects"
            ]
        }
    ],
    "site": [
        {
            "name": "sites",
            "subComponents": [
                "get-a-site",
                "get-sites",
                "create-a-site",
                "modify-a-site",
                "delete-a-site",
                "site-objects"
            ]
        }
    ],
    "subscription": [
        {
            "name": "subscription-forms",
            "subComponents": [
                "get-a-subscription-form",
                "get-subscription-forms",
                "get-subscription-forms-in-a-plan",
                "create-a-subscription-form",
                "modify-a-subscription-form",
                "subscription-form-objects"
            ]
        },
        {
            "name": "subscriptions",
            "subComponents": [
                "get-subscriptions",
                "get-a-subscription",
                "get-subscribers",
                "get-subscription-share-permissions",
                "create-a-subscription",
                "modify-a-subscription",
                "add-subscribers",
                "set-subscription-share-permissions",
                "delete-a-subscription",
                "unsubscribe-a-user",
                "subscription-objects"
            ]
        }
    ],
    "temporary": [
        {
            "name": "temporary-absences",
            "subComponents": [
                "get-temporary-absences",
                "create-a-temporary-absence",
                "delete-a-temporary-absence",
                "temporary-absence-objects"
            ]
        }
    ],
    "upload": [
        {
            "name": "upload-users",
            "subComponents": [
                "upload-a-user-upload-file",
                "upload-an-epic-zipsync-file"
            ]
        }
    ]
}